{"nm":"Main Scene","h":25,"w":76,"meta":{"g":"@lottiefiles/creator 1.45.1"},"layers":[{"ty":4,"nm":"Shine - Coin","sr":1,"st":0,"op":30,"ip":0,"tt":1,"hasMask":false,"ao":0,"ks":{"a":{"a":0,"k":[0,0]},"s":{"a":0,"k":[100,100]},"sk":{"a":0,"k":0},"p":{"a":1,"k":[{"o":{"x":0.167,"y":0.167},"i":{"x":0.833,"y":0.833},"s":[-10,-4.5],"t":0},{"s":[22,-3.5],"t":30}]},"r":{"a":0,"k":0},"sa":{"a":0,"k":0},"o":{"a":1,"k":[{"o":{"x":0.167,"y":0.167},"i":{"x":0.833,"y":0.833},"s":[100],"t":0},{"s":[100],"t":30}]}},"shapes":[{"ty":"gr","nm":"Group 3","it":[{"ty":"rc","nm":"Rectangle 1","d":1,"p":{"a":0,"k":[14,16]},"r":{"a":0,"k":0},"s":{"a":0,"k":[4,32]}},{"ty":"fl","nm":"Fill","c":{"a":0,"k":[1,1,1]},"r":1,"o":{"a":0,"k":100}},{"ty":"tr","a":{"a":0,"k":[14,16.022]},"s":{"a":0,"k":[100,100]},"sk":{"a":0,"k":0},"p":{"a":0,"k":[7.852,15.605]},"r":{"a":0,"k":22},"sa":{"a":0,"k":0},"o":{"a":0,"k":40}}]}],"ind":1,"tp":7},{"ty":4,"nm":"Star","sr":1,"st":0,"op":150,"ip":0,"hasMask":false,"ao":0,"ks":{"a":{"a":0,"k":[24.357,15.15]},"s":{"a":0,"k":[100,100]},"sk":{"a":0,"k":0},"p":{"a":0,"k":[14.357,12.65]},"r":{"a":0,"k":0},"sa":{"a":0,"k":0},"o":{"a":0,"k":100}},"shapes":[{"ty":"gr","nm":"Group 1","it":[{"ty":"sh","nm":"Path 1","d":1,"ks":{"a":0,"k":{"c":true,"i":[[0,0],[-0.148,-0.456],[0,0],[-0.214,0],[0,0],[0.388,-0.282],[0,0],[-0.066,-0.204],[0,0],[0.388,0.282],[0,0],[0.173,-0.126],[0,0],[-0.148,0.456],[0,0],[0.173,0.126],[0,0],[-0.479,0],[0,0],[-0.066,0.204],[0,0]],"o":[[0.148,-0.456],[0,0],[0.066,0.204],[0,0],[0.479,0],[0,0],[-0.173,0.126],[0,0],[0.148,0.456],[0,0],[-0.173,-0.126],[0,0],[-0.388,0.282],[0,0],[0.066,-0.204],[0,0],[-0.388,-0.282],[0,0],[0.214,0],[0,0],[0,0]],"v":[[23.887,10.816],[24.827,10.816],[25.638,13.312],[26.109,13.654],[28.734,13.654],[29.024,14.549],[26.901,16.092],[26.721,16.645],[27.532,19.141],[26.771,19.694],[24.648,18.151],[24.066,18.151],[21.943,19.694],[21.182,19.141],[21.993,16.645],[21.813,16.092],[19.689,14.549],[19.98,13.654],[22.605,13.654],[23.075,13.312],[23.887,10.816]]}}},{"ty":"fl","nm":"Fill","c":{"a":0,"k":[1,1,1]},"r":1,"o":{"a":0,"k":100}},{"ty":"tr","a":{"a":0,"k":[24.357,15.15]},"s":{"a":0,"k":[100,100]},"sk":{"a":0,"k":0},"p":{"a":0,"k":[24.357,15.15]},"r":{"a":0,"k":0},"sa":{"a":0,"k":0},"o":{"a":0,"k":100}}]}],"ind":2},{"ty":4,"nm":"Shape Layer 1","sr":1,"st":0,"op":150,"ip":0,"hd":true,"hasMask":false,"ao":0,"ks":{"a":{"a":0,"k":[24.502,15.499]},"s":{"a":0,"k":[100,100]},"sk":{"a":0,"k":0},"p":{"a":0,"k":[20.502,13.999]},"r":{"a":0,"k":0},"sa":{"a":0,"k":0},"o":{"a":0,"k":100}},"shapes":[{"ty":"gr","nm":"Group 2","it":[{"ty":"sh","nm":"Path 2","d":1,"ks":{"a":0,"k":{"c":true,"i":[[0,0],[0.383,-0.981],[2.51,-0.81],[0.936,0],[0,4.905],[-4.893,0],[0,-4.862]],"o":[[0,1.109],[-0.936,2.474],[-0.851,0.299],[-4.893,0.043],[0,-4.905],[4.851,0],[0,0]],"v":[[33.33,15.499],[32.735,18.698],[27.246,23.902],[24.523,24.328],[15.673,15.499],[24.523,6.671],[33.33,15.499]]}}},{"ty":"fl","nm":"Fill","c":{"a":0,"k":[1,0.726,0.271]},"r":1,"o":{"a":0,"k":100}},{"ty":"tr","a":{"a":0,"k":[0,0]},"s":{"a":0,"k":[100,100]},"sk":{"a":0,"k":0},"p":{"a":0,"k":[0,0]},"r":{"a":0,"k":0},"sa":{"a":0,"k":0},"o":{"a":0,"k":100}}]}],"ind":3},{"ty":4,"nm":"Shape Layer 3","sr":1,"st":0,"op":150,"ip":0,"hasMask":false,"ao":0,"ks":{"a":{"a":0,"k":[24.5,15.5]},"s":{"a":0,"k":[100,100]},"sk":{"a":0,"k":0},"p":{"a":0,"k":[14.5,14]},"r":{"a":0,"k":0},"sa":{"a":0,"k":0},"o":{"a":0,"k":100}},"shapes":[{"ty":"gr","nm":"Group 4","it":[{"ty":"sh","nm":"Path 3","d":1,"ks":{"a":0,"k":{"c":true,"i":[[0,0],[0,-5.471],[0.427,-1.095],[0,0],[2.823,-0.911],[0,0],[0.937,-0.033],[0,0],[0,0],[0,5.529],[-5.514,0]],"o":[[5.448,0],[0,1.25],[0,0],[-1.048,2.77],[0,0],[-0.794,0.278],[0,0],[0,0],[-5.49,0.048],[0,-5.516],[0,0]],"v":[[24.527,5.568],[34.432,15.5],[33.764,19.096],[33.758,19.111],[27.593,24.952],[27.556,24.964],[24.932,25.425],[24.527,25.432],[24.514,25.432],[14.568,15.5],[24.527,5.568]]}}},{"ty":"gs","nm":"Stroke","e":{"a":0,"k":[31.436,26.916]},"g":{"p":2,"k":{"a":0,"k":[0,1,0.902,0.514,1,1,0.667,0,0,1,1,1]}},"t":1,"a":{"a":0,"k":0},"h":{"a":0,"k":0},"s":{"a":0,"k":[17.324,5.073]},"lc":1,"lj":1,"ml":4,"o":{"a":0,"k":100},"w":{"a":0,"k":3.136}},{"ty":"tr","a":{"a":0,"k":[24.5,15.522]},"s":{"a":0,"k":[100,100]},"sk":{"a":0,"k":0},"p":{"a":0,"k":[24.5,14.5]},"r":{"a":0,"k":0},"sa":{"a":0,"k":0},"o":{"a":0,"k":100}}]},{"ty":"gr","nm":"Group 5","it":[{"ty":"sh","nm":"Path 4","d":1,"ks":{"a":0,"k":{"c":true,"i":[[0,0],[0.499,-1.278],[3.27,-1.055],[1.219,0],[0,6.389],[-6.373,0],[0,-6.333]],"o":[[0,1.444],[-1.219,3.222],[-1.108,0.389],[-6.373,0.055],[0,-6.389],[6.318,0],[0,0]],"v":[[36,15.5],[35.224,19.666],[28.075,26.444],[24.528,27],[13,15.5],[24.528,4],[36,15.5]]}}},{"ty":"fl","nm":"Fill","c":{"a":0,"k":[1,0.843,0.353]},"r":1,"o":{"a":0,"k":100}},{"ty":"tr","a":{"a":0,"k":[24.5,15.5]},"s":{"a":0,"k":[100,100]},"sk":{"a":0,"k":0},"p":{"a":0,"k":[24.5,14.5]},"r":{"a":0,"k":0},"sa":{"a":0,"k":0},"o":{"a":0,"k":100}}]}],"ind":4},{"ty":4,"nm":"Offer","sr":1,"st":0,"op":150,"ip":0,"hasMask":false,"ao":0,"ks":{"a":{"a":0,"k":[59.053,19.517]},"s":{"a":0,"k":[100,100]},"sk":{"a":0,"k":0},"p":{"a":0,"k":[47.053,15.017]},"r":{"a":0,"k":0},"sa":{"a":0,"k":0},"o":{"a":0,"k":100}},"shapes":[{"ty":"gr","nm":"Group 6","it":[{"ty":"sh","nm":"Path 5","d":1,"ks":{"a":0,"k":{"c":true,"i":[[0,0],[0.547,0.307],[0.32,0.54],[0,0.687],[-0.32,0.54],[-0.547,0.307],[-0.653,0],[-0.54,-0.307],[-0.313,-0.547],[0,-0.68],[0.32,-0.547],[0.547,-0.307],[0.653,0]],"o":[[-0.653,0],[-0.547,-0.307],[-0.32,-0.547],[0,-0.68],[0.32,-0.547],[0.547,-0.307],[0.66,0],[0.547,0.307],[0.32,0.54],[0,0.687],[-0.313,0.54],[-0.547,0.307],[0,0]],"v":[[44.93,23.07],[43.13,22.61],[41.83,21.34],[41.35,19.49],[41.83,17.66],[43.13,16.38],[44.93,15.92],[46.73,16.38],[48.02,17.66],[48.5,19.49],[48.02,21.34],[46.73,22.61],[44.93,23.07]]}}},{"ty":"sh","nm":"Path 6","d":1,"ks":{"a":0,"k":{"c":true,"i":[[0,0],[-0.32,0.187],[-0.18,0.353],[0,0.467],[0.18,0.347],[0.32,0.187],[0.42,0],[0.327,-0.187],[0.18,-0.353],[0,-0.467],[-0.18,-0.353],[-0.32,-0.193],[-0.42,0]],"o":[[0.42,0],[0.32,-0.193],[0.18,-0.353],[0,-0.467],[-0.18,-0.353],[-0.32,-0.187],[-0.42,0],[-0.32,0.187],[-0.18,0.347],[0,0.467],[0.18,0.353],[0.327,0.187],[0,0]],"v":[[44.93,21.82],[46.04,21.54],[46.79,20.72],[47.06,19.49],[46.79,18.27],[46.04,17.46],[44.93,17.18],[43.81,17.46],[43.06,18.27],[42.79,19.49],[43.06,20.72],[43.81,21.54],[44.93,21.82]]}}},{"ty":"sh","nm":"Path 7","d":1,"ks":{"a":0,"k":{"c":true,"i":[[0,0],[0,0],[0,0],[0,0],[0,0],[0,0],[0,0],[0,0],[0,0],[0,0],[0,0]],"o":[[0,0],[0,0],[0,0],[0,0],[0,0],[0,0],[0,0],[0,0],[0,0],[0,0],[0,0]],"v":[[53.852,16.02],[53.852,17.15],[50.942,17.15],[50.942,18.94],[53.172,18.94],[53.172,20.05],[50.942,20.05],[50.942,23],[49.542,23],[49.542,16.02],[53.852,16.02]]}}},{"ty":"sh","nm":"Path 8","d":1,"ks":{"a":0,"k":{"c":true,"i":[[0,0],[0,0],[0,0],[0,0],[0,0],[0,0],[0,0],[0,0],[0,0],[0,0],[0,0]],"o":[[0,0],[0,0],[0,0],[0,0],[0,0],[0,0],[0,0],[0,0],[0,0],[0,0],[0,0]],"v":[[59.154,16.02],[59.154,17.15],[56.244,17.15],[56.244,18.94],[58.474,18.94],[58.474,20.05],[56.244,20.05],[56.244,23],[54.844,23],[54.844,16.02],[59.154,16.02]]}}},{"ty":"sh","nm":"Path 9","d":1,"ks":{"a":0,"k":{"c":true,"i":[[0,0],[0,0],[0,0],[0,0],[0,0],[0,0],[0,0],[0,0],[0,0],[0,0],[0,0],[0,0],[0,0]],"o":[[0,0],[0,0],[0,0],[0,0],[0,0],[0,0],[0,0],[0,0],[0,0],[0,0],[0,0],[0,0],[0,0]],"v":[[61.547,17.15],[61.547,18.9],[63.897,18.9],[63.897,20.01],[61.547,20.01],[61.547,21.86],[64.197,21.86],[64.197,23],[60.147,23],[60.147,16.01],[64.197,16.01],[64.197,17.15],[61.547,17.15]]}}},{"ty":"sh","nm":"Path 10","d":1,"ks":{"a":0,"k":{"c":true,"i":[[0,0],[0,0],[0,0],[0,0],[0,0],[0,0],[0,0],[-0.38,-0.193],[-0.187,-0.327],[0,-0.4],[0.267,-0.373],[0.527,-0.14],[0,0],[0,0]],"o":[[0,0],[0,0],[0,0],[0,0],[0,0],[0,0],[0.54,0],[0.38,0.187],[0.193,0.32],[0,0.46],[-0.267,0.367],[0,0],[0,0],[0,0]],"v":[[69.069,23],[67.529,20.28],[66.869,20.28],[66.869,23],[65.469,23],[65.469,16.02],[68.089,16.02],[69.469,16.31],[70.319,17.08],[70.609,18.16],[70.209,19.41],[69.019,20.17],[70.689,23],[69.069,23]]}}},{"ty":"sh","nm":"Path 11","d":1,"ks":{"a":0,"k":{"c":true,"i":[[0,0],[0,0],[-0.187,0.18],[0,0.327],[0.187,0.173],[0.38,0],[0,0],[0,0]],"o":[[0,0],[0.38,0],[0.187,-0.187],[0,-0.32],[-0.187,-0.18],[0,0],[0,0],[0,0]],"v":[[66.869,19.23],[68.039,19.23],[68.889,18.96],[69.169,18.19],[68.889,17.45],[68.039,17.18],[66.869,17.18],[66.869,19.23]]}}},{"ty":"sh","nm":"Path 12","d":1,"ks":{"a":0,"k":{"c":true,"i":[[0,0],[0.393,0.167],[0.227,0.313],[0.007,0.427],[0,0],[-0.18,-0.167],[-0.32,0],[-0.187,0.153],[0,0.253],[0.127,0.133],[0.193,0.073],[0.333,0.093],[0.287,0.127],[0.207,0.26],[0,0.44],[-0.207,0.307],[-0.373,0.16],[-0.48,0],[-0.447,-0.353],[-0.047,-0.627],[0,0],[0.193,0.153],[0.313,0],[0.167,-0.14],[0,-0.267],[-0.12,-0.127],[-0.18,-0.08],[-0.333,-0.1],[-0.287,-0.133],[-0.207,-0.267],[0,-0.433],[0.193,-0.32],[0.373,-0.193],[0.513,0]],"o":[[-0.487,0],[-0.387,-0.167],[-0.227,-0.313],[0,0],[0.02,0.287],[0.187,0.167],[0.327,0],[0.187,-0.16],[0,-0.207],[-0.127,-0.133],[-0.187,-0.08],[-0.453,-0.133],[-0.28,-0.133],[-0.2,-0.267],[0,-0.413],[0.207,-0.307],[0.373,-0.167],[0.72,0],[0.453,0.347],[0,0],[-0.013,-0.24],[-0.187,-0.16],[-0.273,0],[-0.16,0.14],[0,0.187],[0.127,0.12],[0.187,0.073],[0.453,0.133],[0.287,0.133],[0.207,0.267],[0,0.373],[-0.193,0.32],[-0.373,0.187],[0,0]],"v":[[74.286,23.07],[72.966,22.82],[72.046,22.1],[71.696,20.99],[73.196,20.99],[73.496,21.67],[74.256,21.92],[75.026,21.69],[75.306,21.07],[75.116,20.56],[74.636,20.25],[73.856,19.99],[72.746,19.6],[72.016,19.01],[71.716,17.95],[72.026,16.87],[72.896,16.17],[74.176,15.92],[75.926,16.45],[76.676,17.91],[75.136,17.91],[74.826,17.32],[74.076,17.08],[73.416,17.29],[73.176,17.9],[73.356,18.37],[73.816,18.67],[74.596,18.93],[75.706,19.33],[76.446,19.93],[76.756,20.98],[76.466,22.02],[75.616,22.79],[74.286,23.07]]}}},{"ty":"fl","nm":"Fill","c":{"a":0,"k":[0.678,0.463,0.012]},"r":1,"o":{"a":0,"k":100}},{"ty":"tr","a":{"a":0,"k":[0,0]},"s":{"a":0,"k":[100,100]},"sk":{"a":0,"k":0},"p":{"a":0,"k":[0,0]},"r":{"a":0,"k":0},"sa":{"a":0,"k":0},"o":{"a":0,"k":100}}]}],"ind":5},{"ty":4,"nm":"Stroke","sr":1,"st":0,"op":150,"ip":0,"hasMask":false,"ao":0,"ks":{"a":{"a":0,"k":[20.5,19.022]},"s":{"a":0,"k":[100,100]},"sk":{"a":0,"k":0},"p":{"a":0,"k":[16.5,15.522]},"r":{"a":0,"k":0},"sa":{"a":0,"k":0},"o":{"a":0,"k":100}},"shapes":[{"ty":"st","nm":"Stroke","lc":1,"lj":1,"ml":4,"o":{"a":0,"k":100},"w":{"a":0,"k":1},"c":{"a":0,"k":[0.831,0.573,0.149]}},{"ty":"fl","nm":"Fill","c":{"a":0,"k":[1,0.988,0.949]},"r":1,"o":{"a":0,"k":100}}],"ind":6},{"ty":4,"nm":"Ellipse 1","sr":1,"st":0,"op":150,"ip":0,"hasMask":false,"td":1,"ao":0,"ks":{"a":{"a":0,"k":[0,0]},"s":{"a":0,"k":[131.053,132.983]},"sk":{"a":0,"k":0},"p":{"a":0,"k":[14.633,12.5]},"r":{"a":0,"k":0},"sa":{"a":0,"k":0},"o":{"a":0,"k":100}},"shapes":[{"ty":"el","nm":"Ellipse Path 1","d":1,"p":{"a":0,"k":[0,0]},"s":{"a":0,"k":[18,18]}},{"ty":"fl","nm":"Fill","c":{"a":0,"k":[1,1,1]},"r":1,"o":{"a":0,"k":100}}],"ind":7},{"ty":4,"nm":"Stroke","sr":1,"st":0,"op":150,"ip":0,"hasMask":false,"ao":0,"ks":{"a":{"a":0,"k":[20.5,19.022]},"s":{"a":0,"k":[100,100]},"sk":{"a":0,"k":0},"p":{"a":0,"k":[10.5,14.522]},"r":{"a":0,"k":0},"sa":{"a":0,"k":0},"o":{"a":0,"k":100}},"shapes":[{"ty":"sh","nm":"Trim path","d":1,"ks":{"a":0,"k":{"c":true,"i":[[0,-4.691],[0,0],[4.691,0],[0,0],[0,4.691],[0,0],[-4.691,0],[0,0]],"o":[[0,0],[0,4.691],[0,0],[-4.691,0],[0,0],[0,-4.691],[0,0],[4.691,0]],"v":[[83.5,19],[83.5,19],[75,27.5],[29,27.5],[20.5,19],[20.5,19],[29,10.5],[75,10.5]]}}},{"ty":"st","nm":"Stroke","lc":1,"lj":1,"ml":4,"o":{"a":0,"k":100},"w":{"a":0,"k":1},"c":{"a":0,"k":[0.831,0.573,0.149]}},{"ty":"tm","nm":"Trim Path","e":{"a":1,"k":[{"o":{"x":0.167,"y":0.167},"i":{"x":0.833,"y":0.833},"s":[44],"t":31},{"o":{"x":0.167,"y":0.167},"i":{"x":0.833,"y":0.833},"s":[7],"t":61},{"s":[44],"t":90}]},"o":{"a":1,"k":[{"o":{"x":0.167,"y":0.167},"i":{"x":0.833,"y":0.833},"s":[0],"t":31},{"s":[360],"t":90}]},"s":{"a":1,"k":[{"o":{"x":0.167,"y":0.167},"i":{"x":0.833,"y":0.833},"s":[60],"t":31},{"o":{"x":0.167,"y":0.167},"i":{"x":0.833,"y":0.833},"s":[94.424],"t":61},{"s":[51],"t":90}]},"m":1}],"ind":8},{"ty":4,"nm":"Group 8","sr":1,"st":0,"op":150,"ip":0,"hasMask":false,"ao":0,"ks":{"a":{"a":0,"k":[0,0]},"s":{"a":0,"k":[100,100]},"sk":{"a":0,"k":0},"p":{"a":0,"k":[-10,-4.5]},"r":{"a":0,"k":0},"sa":{"a":0,"k":0},"o":{"a":0,"k":100}},"shapes":[{"ty":"gr","nm":"Group 8","it":[{"ty":"rc","nm":"Rectangle 2","d":1,"p":{"a":0,"k":[52,19]},"r":{"a":0,"k":8.5},"s":{"a":0,"k":[63,17]}},{"ty":"st","nm":"Stroke","lc":1,"lj":1,"ml":4,"o":{"a":0,"k":100},"w":{"a":0,"k":1},"c":{"a":0,"k":[1,0.851,0.251]}},{"ty":"fl","nm":"Fill","c":{"a":0,"k":[1,0.988,0.949]},"r":1,"o":{"a":0,"k":100}},{"ty":"tr","a":{"a":0,"k":[52,19.022]},"s":{"a":0,"k":[100,100]},"sk":{"a":0,"k":0},"p":{"a":0,"k":[52,19.022]},"r":{"a":0,"k":0},"sa":{"a":0,"k":0},"o":{"a":0,"k":100}}]}],"ind":9}],"v":"5.7.0","fr":30,"op":100,"ip":0,"assets":[]}
